newtestpackage/__init__.py
newtestpackage/newtestpackage.py
NewTestPackage-0.0.2.dist-info/LICENSE
NewTestPackage-0.0.2.dist-info/METADATA
NewTestPackage-0.0.2.dist-info/WHEEL
NewTestPackage-0.0.2.dist-info/top_level.txt
NewTestPackage-0.0.2.dist-info/RECORD
