Metadata-Version: 2.1
Name: NewTestPackage
Version: 0.0.2
Summary: to just test geo 
Home-page: https://github.com/Maherhassanali/NewTestPackage
Author: maher
Author-email: maherarmoongisanalyst@gmail.com
License: MIT license
Keywords: newtestpackage
Classifier: Development Status :: 2 - Pre-Alpha
Classifier: Intended Audience :: Developers
Classifier: License :: OSI Approved :: MIT License
Classifier: Natural Language :: English
Classifier: Programming Language :: Python :: 3
Classifier: Programming Language :: Python :: 3.7
Classifier: Programming Language :: Python :: 3.8
Classifier: Programming Language :: Python :: 3.9
Classifier: Programming Language :: Python :: 3.10
Requires-Python: >=3.7
License-File: LICENSE
